rpi_oled_display/PixelOperator.ttf
rpi_oled_display/__init__.py
rpi_oled_display/display_sh1106.py
rpi_oled_display/display_ssd1306.py
rpi_oled_display/oled_runner.py
rpi_oled_display-1.0.2.dist-info/METADATA
rpi_oled_display-1.0.2.dist-info/WHEEL
rpi_oled_display-1.0.2.dist-info/entry_points.txt
rpi_oled_display-1.0.2.dist-info/top_level.txt
rpi_oled_display-1.0.2.dist-info/RECORD
