Metadata-Version: 2.4
Name: rpi-oled-display
Version: 1.0.2
Summary: Display system stats on Raspberry Pi OLED (SH1106/SSD1306)
Home-page: https://github.com/honeer/RaspberryPi-OLED
Author: honeer
Classifier: Programming Language :: Python :: 3
Classifier: License :: OSI Approved :: MIT License
Classifier: Operating System :: POSIX :: Linux
Requires-Python: >=3.7
Requires-Dist: luma.oled
Requires-Dist: adafruit-blinka
Requires-Dist: Pillow
